TracOhlohBadge-1.1.dist-info/DESCRIPTION.rst
TracOhlohBadge-1.1.dist-info/METADATA
TracOhlohBadge-1.1.dist-info/RECORD
TracOhlohBadge-1.1.dist-info/WHEEL
TracOhlohBadge-1.1.dist-info/entry_points.txt
TracOhlohBadge-1.1.dist-info/metadata.json
TracOhlohBadge-1.1.dist-info/top_level.txt
ohlohbadge/__init__.py
ohlohbadge/macro.py
